kapt_templates/__init__.py
kapt_templates/apps.py
kapt_templates/checks.py
kapt_templates/handlebars/catalog/partials/event_results_list.html
kapt_templates/handlebars/catalog/partials/results_list.html
kapt_templates/locale/de/LC_MESSAGES/django.mo
kapt_templates/locale/de/LC_MESSAGES/django.po
kapt_templates/locale/es/LC_MESSAGES/django.mo
kapt_templates/locale/es/LC_MESSAGES/django.po
kapt_templates/locale/fr/LC_MESSAGES/django.mo
kapt_templates/locale/fr/LC_MESSAGES/django.po
kapt_templates/locale/it/LC_MESSAGES/django.mo
kapt_templates/locale/it/LC_MESSAGES/django.po
kapt_templates/static/img/logo_kapt.png
kapt_templates/static/img/logo_kapt_white.png
kapt_templates/templates/403.html
kapt_templates/templates/404.html
kapt_templates/templates/500.html
kapt_templates/templates/503.html
kapt_templates/templates/_base.html
kapt_templates/templates/aldryn_newsblog/_article_detail.html
kapt_templates/templates/aldryn_newsblog/_base.html
kapt_templates/templates/aldryn_newsblog/article_detail.html
kapt_templates/templates/aldryn_newsblog/base.html
kapt_templates/templates/base.html
kapt_templates/templates/catalog/_activity_detail.html
kapt_templates/templates/catalog/_activity_results_list.html
kapt_templates/templates/catalog/activity_detail.html
kapt_templates/templates/catalog/activity_results_list.html
kapt_templates/templates/catalog/event_results_list.html
kapt_templates/templates/catalog/partials/address.html
kapt_templates/templates/catalog/partials/business_informations.html
kapt_templates/templates/catalog/partials/few_results.html
kapt_templates/templates/catalog/partials/few_results_link.html
kapt_templates/templates/catalog/partials/gallery/carrousel.html
kapt_templates/templates/catalog/partials/rating.html
kapt_templates/templates/catalog/partials/rating_logo.html
kapt_templates/templates/catalog/partials/social_share.html
kapt_templates/templates/catalog/partials/type.html
kapt_templates/templates/catalog/partials/wishlist_controls.html
kapt_templates-5.16.5.dist-info/METADATA
kapt_templates-5.16.5.dist-info/WHEEL
kapt_templates-5.16.5.dist-info/RECORD
