Metadata-Version: 2.1
Name: kapt-templates
Version: 5.16.5
Summary: Templates for Kapt modules
License: Proprietary
Author: KAPT dev team
Author-email: dev@kapt.mobi
Requires-Python: >=2.7, !=3.0.*, !=3.1.*, !=3.2.*, !=3.3.*, !=3.4.*, !=3.5.*, !=3.6.*, !=3.7.*
Classifier: License :: Other/Proprietary License
Classifier: Programming Language :: Python :: 2
Classifier: Programming Language :: Python :: 2.7
Classifier: Programming Language :: Python :: 3
Classifier: Programming Language :: Python :: 3.8
Classifier: Programming Language :: Python :: 3.9
Classifier: Programming Language :: Python :: 3.10
Classifier: Programming Language :: Python :: 3.11
Classifier: Programming Language :: Python :: 3.12
Requires-Dist: Django (>=1.11)
Requires-Dist: django-cms (>=3.5,<4.0)
Requires-Dist: django-embed-video (>=1.3.3,<2.0.0)
Requires-Dist: django-widget-tweaks (>=1.4.12,<2.0.0)
Requires-Dist: djangocms-page-meta (>=1.0.1,<2.0.0)
